{
  "id": "357e8757-36a7-4796-adff-ecf24340aa6a",
  "url": "https://drscdn.500px.org/photo/282322229/q%3D80_m%3D1500/v2?webp=true&sig=fcb417d8ed492416fde79f6b278bcf93481c553f06a470065eff92257810e42c",
  "external_url": "https://500px.com/photo/282322229/pont-des-arts-el-institut-de-france-by-juan-carlos-herv%C3%A1s-mart%C3%ADnez",
  "content_text": "Pont des Arts el Institut de France",
  "_meta": {
    "venue": {
      "name": "500px",
      "url": "https://500px.com"
    },
    "bezel_color": "light",
    "camera_settings": {
      "iso": "ISO 320",
      "shutter_speed": "8s",
      "f": "ƒ/16"
    }
  },
  "author": {
    "name": "Juan Carlos Hervás Martínez",
    "url": "https://500px.com/juancarloshervasmartinez",
    "avatar": "https://drscdn.500px.org/user_avatar/4386640/q%3D85_w%3D100_h%3D100/v2?webp=true&v=3&sig=11ee55b95cbad81873f5e303009c3fb243a5c653617779335417ffb5b7af2eb3"
  },
  "tags": [
    "moon",
    "pont",
    "bridge",
    "institut de france",
    "france",
    "paris",
    "night",
    "architecture",
    "cityscape",
    "nuit",
    "nocturna"
  ]
}
