{
  "id": "441dddf1-45c9-48e2-b3cc-a47d9e3a6292",
  "url": "https://drscdn.500px.org/photo/282357717/q%3D80_m%3D2000/v2?webp=true&sig=46d147ea7ddb0125e69218f3de956f81e1b97408612f47abde61a006b1c1418a",
  "external_url": "https://500px.com/photo/282357717/%E8%83%A1%E6%9D%A8%E9%AD%85%E5%BD%B1-19-by-beatles1919",
  "content_text": "胡杨魅影-19",
  "_meta": {
    "venue": {
      "name": "500px",
      "url": "https://500px.com"
    },
    "bezel_color": "light",
    "camera_settings": {}
  },
  "author": {
    "name": "beatles1919",
    "url": "https://500px.com/vcg-beatles1919",
    "avatar": "https://drscdn.500px.org/user_avatar/23827121/q%3D85_w%3D100_h%3D100/v2?webp=true&v=12&sig=da439954e936e42d479d4959c181c94f633edbf19b281e455ff3786f35c1fadc"
  },
  "tags": [
    "胡杨",
    "色彩",
    "倒影",
    "日落",
    "青春",
    "风华正茂"
  ]
}
