{
  "id": "bbe6d3a2-5e8c-4bbb-8937-48d476abf553",
  "url": "https://drscdn.500px.org/photo/282318019/q%3D80_m%3D2000/v2?webp=true&sig=0ec89e075d81a576f2c18973e34275bb927a192a58b02b7a775cb5f34d57014c",
  "external_url": "https://500px.com/photo/282318019/you-better-leave-this-dream-alone-and-try-to-find-another-by-michael-clyne",
  "content_text": "You better leave this dream alone and try to find another",
  "_meta": {
    "venue": {
      "name": "500px",
      "url": "https://500px.com"
    },
    "bezel_color": "light",
    "camera_settings": {
      "iso": "ISO 360",
      "shutter_speed": "1/125s",
      "f": "ƒ/5"
    }
  },
  "author": {
    "name": "Michael Clyne",
    "url": "https://500px.com/fallsroad",
    "avatar": "https://drscdn.500px.org/user_avatar/11737223/q%3D85_w%3D100_h%3D100/v2?webp=true&v=4&sig=b08557fd42ae73545b2f0ee70bd3bc7f6cb9c22bfe2f25e6edc7829f111ce16b"
  },
  "tags": [
    "okmulgee",
    "oklahoma",
    "abandoned",
    "decay",
    "industrial",
    "old",
    "brick",
    "building",
    "architecture",
    "doors",
    "windows",
    "broken",
    "black and white",
    "bw",
    "monochrome"
  ]
}
