{
  "id": "ec9618ec-5862-4f20-81a6-2443bbbab06c",
  "url": "https://images.unsplash.com/photo-1536319506488-b48775322c72?ixlib=rb-1.2.1&q=80&fm=jpg&crop=entropy&cs=tinysrgb&w=1080&fit=max&ixid=eyJhcHBfaWQiOjQyOTgyfQ",
  "external_url": "https://unsplash.com/photos/7jBQMHmdVcw",
  "content_text": "Untitiled",
  "_meta": {
    "venue": {
      "name": "Unsplash",
      "url": "https://unsplash.com"
    },
    "camera": {
      "iso": 100,
      "shutter_speed": "1/160",
      "aperture": "2.8",
      "make": "NIKON",
      "model": "COOLPIX P310"
    }
  },
  "author": {
    "name": "cozmicphotos",
    "url": "https://unsplash.com/@cozmicphotos",
    "avatar": "https://images.unsplash.com/profile-1526973680584-a67a64d989e0?ixlib=rb-1.2.1&q=80&fm=jpg&crop=faces&cs=tinysrgb&fit=crop&h=32&w=32"
  },
  "tags": [

  ]
}
