{
  "id": "7f7ae81f-23e4-4d33-8adc-71dd88a1ebdf",
  "url": "https://images.unsplash.com/photo-1545670723-196ed0954986?ixlib=rb-1.2.1&q=80&fm=jpg&crop=entropy&cs=tinysrgb&w=1080&fit=max&ixid=eyJhcHBfaWQiOjQyOTgyfQ",
  "external_url": "https://unsplash.com/photos/FGXqbqbGt5o",
  "content_text": "Untitled",
  "_meta": {
    "venue": {
      "name": "Unsplash",
      "url": "https://unsplash.com"
    },
    "camera": {
      "iso": 500,
      "shutter_speed": "1/200",
      "aperture": "1.8",
      "make": "SONY",
      "model": "ILCE-7"
    }
  },
  "author": {
    "name": "goshua13",
    "url": "https://unsplash.com/@goshua13",
    "avatar": "https://images.unsplash.com/profile-1544980484597-65c2f898b7ef?ixlib=rb-1.2.1&q=80&fm=jpg&crop=faces&cs=tinysrgb&fit=crop&h=32&w=32"
  },
  "tags": [

  ]
}
