{
  "id": "6cc89c3b-c1a8-4959-9393-fd5bffa110ac",
  "url": "https://images.unsplash.com/photo-1500423079914-b65af272b8db?ixlib=rb-0.3.5&q=80&fm=jpg&crop=entropy&cs=tinysrgb&w=1080&fit=max&ixid=eyJhcHBfaWQiOjQyOTgyfQ&s=41dd0f688af85d52651bc78e22f50d2b",
  "external_url": "https://unsplash.com/photos/MdgBAkbZ9t4",
  "content_text": "sunset by the ocean",
  "_meta": {
    "venue": {
      "name": "Unsplash",
      "url": "https://unsplash.com"
    },
    "camera": {
      "iso": 1600,
      "shutter_speed": "1/1600",
      "aperture": "4.0",
      "make": "FUJIFILM",
      "model": "X-Pro1"
    }
  },
  "author": {
    "name": "laski",
    "url": "https://unsplash.com/@laski",
    "avatar": "https://images.unsplash.com/profile-fb-1500423017-7efd7403ff46.jpg?ixlib=rb-0.3.5&q=80&fm=jpg&crop=faces&cs=tinysrgb&fit=crop&h=32&w=32&s=0624cd81f6bcd5e3c88357db6d2b540e"
  },
  "tags": [

  ]
}
