{
  "id": "459f9ee9-4819-4b44-bb1d-17f400d077a0",
  "url": "https://images.unsplash.com/photo-1552775838-b0c8d3b881fb?ixlib=rb-1.2.1&q=80&fm=jpg&crop=entropy&cs=tinysrgb&w=1080&fit=max&ixid=eyJhcHBfaWQiOjQyOTgyfQ",
  "external_url": "https://unsplash.com/photos/pM9pkc9J918",
  "content_text": "Trusty old tool photographed on the garage floor.   \r\n\r\nInteresting how you sometimes never notice what is right there before you everyday.  The background has an effect like a filter was applied…actually, the garage floor just turns out to be rather interesting when examined up close.",
  "_meta": {
    "venue": {
      "name": "Unsplash",
      "url": "https://unsplash.com"
    },
    "camera": {
      "iso": 200,
      "shutter_speed": null,
      "aperture": null,
      "make": "Panasonic",
      "model": "DMC-G7"
    }
  },
  "author": {
    "name": "lazycreekimages",
    "url": "https://unsplash.com/@lazycreekimages",
    "avatar": "https://images.unsplash.com/profile-1552583819009-360e9c86052d?ixlib=rb-1.2.1&q=80&fm=jpg&crop=faces&cs=tinysrgb&fit=crop&h=32&w=32"
  },
  "tags": [

  ]
}
