{
  "id": "bd49594a-c99b-42c2-9663-c03e2f5846cf",
  "url": "https://images.unsplash.com/photo-1590739844885-44635e95b1b2?crop=entropy&cs=tinysrgb&fit=max&fm=jpg&ixid=Mnw0Mjk4MnwwfDF8YWxsfHx8fHx8fHx8MTYyMzE4NzI4Nw&ixlib=rb-1.2.1&q=80&w=1080",
  "external_url": "https://unsplash.com/photos/E61v6o0x4j8",
  "content_text": "Purple tulip camp",
  "_meta": {
    "venue": {
      "name": "Unsplash",
      "url": "https://unsplash.com"
    },
    "camera": {
      "iso": 100,
      "shutter_speed": "1/1000",
      "aperture": "1.6",
      "make": "Canon",
      "model": "Canon EOS R"
    }
  },
  "author": {
    "name": "sandro",
    "url": "https://unsplash.com/@sandro",
    "avatar": "https://images.unsplash.com/profile-1570874240659-b9a0bdbc9de6image?ixlib=rb-1.2.1&q=80&fm=jpg&crop=faces&cs=tinysrgb&fit=crop&h=32&w=32"
  },
  "tags": [

  ]
}
