{
  "id": "bad60afb-cac7-4777-9ec8-48ef018c0ca4",
  "url": "https://images.unsplash.com/photo-1545499026-702db711b529?ixlib=rb-1.2.1&q=80&fm=jpg&crop=entropy&cs=tinysrgb&w=1080&fit=max&ixid=eyJhcHBfaWQiOjQyOTgyfQ",
  "external_url": "https://unsplash.com/photos/0kLicsfyjow",
  "content_text": "Untitled",
  "_meta": {
    "venue": {
      "name": "Unsplash",
      "url": "https://unsplash.com"
    },
    "camera": {
      "iso": 100,
      "shutter_speed": "1/30",
      "aperture": "5.6",
      "make": "Canon",
      "model": "Canon EOS 5D Mark II"
    }
  },
  "author": {
    "name": "plloyd",
    "url": "https://unsplash.com/@plloyd",
    "avatar": "https://images.unsplash.com/profile-1540609965885-b5da0a95383c?ixlib=rb-1.2.1&q=80&fm=jpg&crop=faces&cs=tinysrgb&fit=crop&h=32&w=32"
  },
  "tags": [

  ]
}
