{
  "id": "ee89ec17-bd66-4ef1-87ef-2be13b90507a",
  "url": "https://images.unsplash.com/photo-1545618800-ac6f17d480a9?ixlib=rb-1.2.1&q=80&fm=jpg&crop=entropy&cs=tinysrgb&w=1080&fit=max&ixid=eyJhcHBfaWQiOjQyOTgyfQ",
  "external_url": "https://unsplash.com/photos/xMP18LIsT7s",
  "content_text": "brown staircase",
  "_meta": {
    "venue": {
      "name": "Unsplash",
      "url": "https://unsplash.com"
    },
    "camera": {
      "iso": 400,
      "shutter_speed": "1/5",
      "aperture": "1.8",
      "make": "NIKON CORPORATION",
      "model": "NIKON D610"
    }
  },
  "author": {
    "name": "faylee",
    "url": "https://unsplash.com/@faylee",
    "avatar": "https://images.unsplash.com/profile-1545576086966-fffd73519f3c?ixlib=rb-1.2.1&q=80&fm=jpg&crop=faces&cs=tinysrgb&fit=crop&h=32&w=32"
  },
  "tags": [

  ]
}
